permutations_stats/__about__.py
permutations_stats/__init__.py
permutations_stats/bootstrap.py
permutations_stats/permutations.py
permutations_stats/utils.py
permutations_stats/tests/__init__.py
permutations_stats/tests/brunner_munzel.py
permutations_stats/tests/friedman.py
permutations_stats/tests/mann_whitney.py
permutations_stats/tests/tests.py
permutations_stats/tests/wilcoxon.py
permutations_stats-0.2.dist-info/COPYING
permutations_stats-0.2.dist-info/METADATA
permutations_stats-0.2.dist-info/WHEEL
permutations_stats-0.2.dist-info/top_level.txt
permutations_stats-0.2.dist-info/RECORD
