Metadata-Version: 2.1
Name: permutations-stats
Version: 0.2
Summary: Permutation-based statistical tests in Python
Home-page: https://github.com/trevismd/permutations-stats
Author: Florian Charlier
Author-email: trevis@cascliniques.be
License: GPL-3.0-only
Platform: UNKNOWN
Requires-Python: >=3.7
Requires-Dist: numpy
Requires-Dist: numba
